LICENSE
MANIFEST.in
README.md
setup.cfg
setup.py
scripts/syncrypt
scripts/syncrypt_daemon
syncrypt/RELEASE-VERSION
syncrypt/__init__.py
syncrypt/auth.py
syncrypt/config.py
syncrypt/exceptions.py
syncrypt.egg-info/PKG-INFO
syncrypt.egg-info/SOURCES.txt
syncrypt.egg-info/dependency_links.txt
syncrypt.egg-info/requires.txt
syncrypt.egg-info/top_level.txt
syncrypt/api/__init__.py
syncrypt/api/auth.py
syncrypt/api/client.py
syncrypt/api/resources.py
syncrypt/api/responses.py
syncrypt/app/__init__.py
syncrypt/app/cli.py
syncrypt/app/daemon.py
syncrypt/app/events.py
syncrypt/app/syncrypt.py
syncrypt/app/vault.py
syncrypt/backends/__init__.py
syncrypt/backends/base.py
syncrypt/backends/binary.py
syncrypt/backends/local.py
syncrypt/builtins/__init__.py
syncrypt/builtins/chaos_monkey.py
syncrypt/builtins/log.py
syncrypt/crypt/__init__.py
syncrypt/crypt/aes_cbc.py
syncrypt/crypt/base.py
syncrypt/crypt/plaintext.py
syncrypt/managers/__init__.py
syncrypt/managers/bundle.py
syncrypt/managers/flying_vault.py
syncrypt/managers/revision.py
syncrypt/managers/user_vault_key.py
syncrypt/managers/vault.py
syncrypt/managers/vault_user.py
syncrypt/models/__init__.py
syncrypt/models/base.py
syncrypt/models/bundle.py
syncrypt/models/flying_vault.py
syncrypt/models/identity.py
syncrypt/models/logitem.py
syncrypt/models/revision.py
syncrypt/models/user_vault_key.py
syncrypt/models/vault.py
syncrypt/models/vault_user.py
syncrypt/pipes/__init__.py
syncrypt/pipes/base.py
syncrypt/pipes/compression.py
syncrypt/pipes/crypto.py
syncrypt/pipes/http.py
syncrypt/pipes/io.py
syncrypt/utils/__init__.py
syncrypt/utils/daemon.py
syncrypt/utils/filesystem.py
syncrypt/utils/format.py
syncrypt/utils/logging.py
syncrypt/utils/padding.py
syncrypt/utils/updates.py
syncrypt/utils/version.py
syncrypt/vendor/__init__.py
syncrypt/vendor/bert/__init__.py
syncrypt/vendor/bert/codec.py
syncrypt/vendor/keyart/__init__.py
syncrypt/vendor/keyart/keyart.py