Metadata-Version: 2.1
Name: syncrypt
Version: 0.6.0
Summary: Syncrypt client
Home-page: https://github.com/syncrypt/client
Author: Syncrypt UG
Author-email: support@syncrypt.space
License: UNKNOWN
Platform: UNKNOWN
Classifier: License :: OSI Approved :: GNU General Public License v3 (GPLv3)
Classifier: Intended Audience :: End Users/Desktop
Classifier: Development Status :: 4 - Beta
Classifier: Topic :: Communications :: File Sharing
Classifier: Topic :: System :: Archiving
Classifier: Topic :: Security :: Cryptography
Classifier: Programming Language :: Python :: 3
Classifier: Programming Language :: Python :: 3.6
Classifier: Programming Language :: Python :: 3.7
Classifier: Programming Language :: Python :: 3.8
Requires-Python: >=3.6
Provides-Extra: dist
Provides-Extra: win
Provides-Extra: test
Provides-Extra: uvloop
